qs_kpa/KeyPointAnalysis.py
qs_kpa/__init__.py
qs_kpa/backbone/__init__.py
qs_kpa/backbone/base_arguments.py
qs_kpa/backbone/base_dataset.py
qs_kpa/backbone/base_model.py
qs_kpa/losses/__init__.py
qs_kpa/losses/circle_loss.py
qs_kpa/losses/contrastive_loss.py
qs_kpa/losses/cosine_similarity_loss.py
qs_kpa/losses/multiple_negatives_ranking_loss.py
qs_kpa/losses/online_constrastive_loss.py
qs_kpa/losses/online_triplet_loss.py
qs_kpa/losses/triplet_loss.py
qs_kpa/pseudo_label/__init__.py
qs_kpa/pseudo_label/data_argument.py
qs_kpa/pseudo_label/datasets.py
qs_kpa/pseudo_label/model_argument.py
qs_kpa/pseudo_label/models.py
qs_kpa/train_utils/__init__.py
qs_kpa/train_utils/attentions.py
qs_kpa/train_utils/distance.py
qs_kpa/train_utils/helpers.py
qs_kpa/train_utils/samplers.py
qs_kpa/train_utils/trainer.py
qs_kpa/train_utils/training_argument.py
qs_kpa/utils/__init__.py
qs_kpa/utils/constants.py
qs_kpa/utils/data.py
qs_kpa/utils/hf_argparser.py
qs_kpa/utils/logging.py
qs_kpa/utils/signature.py
qs_kpa-0.0.1.dist-info/LICENSE
qs_kpa-0.0.1.dist-info/METADATA
qs_kpa-0.0.1.dist-info/WHEEL
qs_kpa-0.0.1.dist-info/top_level.txt
qs_kpa-0.0.1.dist-info/RECORD
