Metadata-Version: 2.1
Name: qs-kpa
Version: 0.0.1
Summary: Quantitative Summarization – Key Point Analysis
Home-page: https://github.com/VietHoang1512/KPA
Author: Phan Viet Hoang
Author-email: phanviethoang1512@gmail.com
License: Apache License 2.0
Platform: UNKNOWN
Classifier: Programming Language :: Python :: 3
Classifier: Operating System :: OS Independent
Classifier: Intended Audience :: Developers
Classifier: Natural Language :: English
Requires-Python: >=3.7
Requires-Dist: transformers (<5.0.0,>=4.1.0)
Requires-Dist: tqdm
Requires-Dist: torch (>=1.6.0)
Requires-Dist: numpy
Requires-Dist: sklearn
Requires-Dist: scipy
Requires-Dist: pandas
Requires-Dist: gdown
Requires-Dist: pytorch-metric-learning
